SMCC/Commands.py
SMCC/Constants.py
SMCC/__init__.py
smcc-0.0.2.dist-info/METADATA
smcc-0.0.2.dist-info/WHEEL
smcc-0.0.2.dist-info/licenses/COPYING.LESSER
smcc-0.0.2.dist-info/licenses/LICENSE
smcc-0.0.2.dist-info/RECORD
