Metadata-Version: 2.1
Name: SMCC
Version: 0.0.2
Summary: SMC_core (SMCC) allows for direct communication and control of the Serial-Motor-Controller project via Python-code.
Project-URL: Homepage, https://github.com/Wauro21/SMCC
Project-URL: Bug Tracker, https://github.com/Wauro21/SMCC/issues
Author-email: Mauricio Aravena Cifuentes <maurio.aravena@sansano.usm.cl>
License-File: COPYING.LESSER
License-File: LICENSE
Classifier: License :: OSI Approved :: GNU Lesser General Public License v3 or later (LGPLv3+)
Classifier: Operating System :: OS Independent
Classifier: Programming Language :: Python :: 3
Requires-Python: >=3.7
Requires-Dist: bitarray>=2.7.6
